
<chart>
   <license>ETAS9P33ESHO.945CWK-2XOI1X0-7L</license>
   <chart_type>scatter</chart_type>
   <chart_pref trend_thickness='0' line_thickness='3' point_size='0'/>

   <series_color>
      <color>ffff00</color>
   </series_color>

   <chart_rect x='45' y='20' width='630' height='230' positive_color='cacaca'  />

  <chart_border top_thickness='0'
                 bottom_thickness='0'
                 left_thickness='0'
                 right_thickness='0'
                 color='000000'
                 />

   <tooltip font='Arial' bold='true' size='11' />

   <chart_note type='flag'
               color='000000'
               alpha='90'
               bold='FALSE'
               size='10'
               background_color='ffffe0'
               background_alpha='50'
               shadow='shadow2'
               />

   <chart_grid_h thickness='2' color='ffffff' type='dashed'  />
   <chart_grid_v thickness='2' color='ffffff'   />
		>

   <legend layout='hide' />

   <chart_guide horizontal='TRUE'
             vertical='TRUE'
             thickness='1'
             color='006400'
             alpha='100'
             type='solid'
             snap_h='TRUE'
             snap_v='TRUE'
             radius='3'
             fill_color='006400'
             fill_alpha='100'
             line_color='006400'
             line_alpha='80'
             line_thickness='1'
             text_h_alpha='50'
             text_v_alpha='00'
             suffix_h=' WP'
             decimals='2'
             bold='FALSE'
             size='11'
             text_color='FFFFFF'
             background_color='006400'
             />
   <filter>
      <shadow id='shadow1' distance='2' angle='60' blurX='5' blurY='5' alpha='50' />
      <bevel id='bevel1' angle='45' blurX='5' blurY='5' distance='0' />
      <glow id='glow1' color='ffffff' alpha='0' blurX='7' blurY='7' strength='6' quality='2' inner='FALSE' knockout='FALSE' />
      <glow id='winnerglow' color='ffffff' alpha='0' blurX='7' blurY='7' strength='5' quality='2' inner='FALSE' knockout='FALSE' />
   </filter>

    <axis_value_label>
         <string></string>
          <string> </string>
          <null/>
          <string> </string>
          <string></string>

       </axis_value_label>
		
	   <axis_ticks category_ticks='false'/>

       <axis_value min='0' max='1' steps='4'  decimals='2' show_min='true' size='13' shadow='shadow2' />     
            <axis_category
               min='0'
               max='60'
               steps='4'
               mode='all'
               decimals='0'
               size='13'
               shadow='shadow2'
               />

       <axis_category_label>
          <string>Kickoff</string>
          <string></string>
          <string>Halftime</string>
          <string></string>
          <string>End</string>

       </axis_category_label>


        <chart_data>
       <row>
	      <null/><number>x</number><number>y</number><number>x</number><number>y</number><number>x</number><number>y</number><number>x</number><number>y</number><number>x</number><number>y</number><number>x</number><number>y</number><number>x</number><number>y</number><number>x</number><number>y</number><number>x</number><number>y</number><number>x</number><number>y</number><number>x</number><number>y</number><number>x</number><number>y</number><number>x</number><number>y</number><number>x</number><number>y</number><number>x</number><number>y</number><number>x</number><number>y</number><number>x</number><number>y</number><number>x</number><number>y</number><number>x</number><number>y</number><number>x</number><number>y</number><number>x</number><number>y</number><number>x</number><number>y</number><number>x</number><number>y</number><number>x</number><number>y</number><number>x</number><number>y</number><number>x</number><number>y</number><number>x</number><number>y</number><number>x</number><number>y</number><number>x</number><number>y</number><number>x</number><number>y</number><number>x</number><number>y</number><number>x</number><number>y</number><number>x</number><number>y</number><number>x</number><number>y</number><number>x</number><number>y</number><number>x</number><number>y</number><number>x</number><number>y</number><number>x</number><number>y</number><number>x</number><number>y</number><number>x</number><number>y</number><number>x</number><number>y</number><number>x</number><number>y</number><number>x</number><number>y</number><number>x</number><number>y</number><number>x</number><number>y</number><number>x</number><number>y</number><number>x</number><number>y</number><number>x</number><number>y</number><number>x</number><number>y</number><number>x</number><number>y</number><number>x</number><number>y</number><number>x</number><number>y</number><number>x</number><number>y</number><number>x</number><number>y</number><number>x</number><number>y</number><number>x</number><number>y</number><number>x</number><number>y</number><number>x</number><number>y</number><number>x</number><number>y</number><number>x</number><number>y</number><number>x</number><number>y</number><number>x</number><number>y</number><number>x</number><number>y</number><number>x</number><number>y</number><number>x</number><number>y</number><number>x</number><number>y</number><number>x</number><number>y</number><number>x</number><number>y</number><number>x</number><number>y</number><number>x</number><number>y</number><number>x</number><number>y</number><number>x</number><number>y</number><number>x</number><number>y</number><number>x</number><number>y</number><number>x</number><number>y</number><number>x</number><number>y</number><number>x</number><number>y</number><number>x</number><number>y</number><number>x</number><number>y</number><number>x</number><number>y</number><number>x</number><number>y</number><number>x</number><number>y</number><number>x</number><number>y</number><number>x</number><number>y</number><number>x</number><number>y</number><number>x</number><number>y</number><number>x</number><number>y</number><number>x</number><number>y</number><number>x</number><number>y</number><number>x</number><number>y</number><number>x</number><number>y</number><number>x</number><number>y</number><number>x</number><number>y</number><number>x</number><number>y</number><number>x</number><number>y</number><number>x</number><number>y</number><number>x</number><number>y</number><number>x</number><number>y</number><number>x</number><number>y</number><number>x</number><number>y</number><number>x</number><number>y</number><number>x</number><number>y</number><number>x</number><number>y</number><number>x</number><number>y</number><number>x</number><number>y</number><number>x</number><number>y</number><number>x</number><number>y</number><number>x</number><number>y</number><number>x</number><number>y</number><number>x</number><number>y</number><number>x</number><number>y</number><number>x</number><number>y</number><number>x</number><number>y</number><number>x</number><number>y</number><number>x</number><number>y</number><number>x</number><number>y</number><number>x</number><number>y</number><number>x</number><number>y</number><number>x</number><number>y</number><number>x</number><number>y</number><number>x</number><number>y</number><number>x</number><number>y</number><number>x</number><number>y</number><number>x</number><number>y</number><number>x</number><number>y</number><number>x</number><number>y</number><number>x</number><number>y</number><number>x</number><number>y</number><number>x</number><number>y</number><number>x</number><number>y</number><number>x</number><number>y</number><number>x</number><number>y</number><number>x</number><number>y</number><number>x</number><number>y</number><number>x</number><number>y</number><number>x</number><number>y</number><number>x</number><number>y</number><number>x</number><number>y</number><number>x</number><number>y</number><number>x</number><number>y</number><number>x</number><number>y</number><number>x</number><number>y</number><number>x</number><number>y</number><number>x</number><number>y</number><number>x</number><number>y</number><number>x</number><number>y</number><number>x</number><number>y</number><number>x</number><number>y</number><number>x</number><number>y</number><number>x</number><number>y</number><number>x</number><number>y</number><number>x</number><number>y</number><number>x</number><number>y</number><number>x</number><number>y</number><number>x</number><number>y</number><number>x</number><number>y</number><number>x</number><number>y</number><number>x</number><number>y</number><number>x</number><number>y</number><number>x</number><number>y</number><number>x</number><number>y</number><number>x</number><number>y</number><number>x</number><number>y</number><number>x</number><number>y</number><number>x</number><number>y</number><number>x</number><number>y</number><number>x</number><number>y</number><number>x</number><number>y</number><number>x</number><number>y</number><number>x</number><number>y</number><number>x</number><number>y</number><number>x</number><number>y</number><number>x</number><number>y</number><number>x</number><number>y</number><number>x</number><number>y</number><number>x</number><number>y</number><number>x</number><number>y</number><number>x</number><number>y</number><number>x</number><number>y</number><number>x</number><number>y</number><number>x</number><number>y</number><number>x</number><number>y</number><number>x</number><number>y</number><number>x</number><number>y</number><number>x</number><number>y</number><number>x</number><number>y</number><number>x</number><number>y</number><number>x</number><number>y</number><number>x</number><number>y</number><number>x</number><number>y</number><number>x</number><number>y</number><number>x</number><number>y</number><number>x</number><number>y</number><number>x</number><number>y</number><number>x</number><number>y</number><number>x</number><number>y</number><number>x</number><number>y</number><number>x</number><number>y</number><number>x</number><number>y</number><number>x</number><number>y</number><number>x</number><number>y</number><number>x</number><number>y</number><number>x</number><number>y</number><number>x</number><number>y</number><number>x</number><number>y</number><number>x</number><number>y</number><number>x</number><number>y</number><number>x</number><number>y</number><number>x</number><number>y</number><number>x</number><number>y</number><number>x</number><number>y</number><number>x</number><number>y</number><number>x</number><number>y</number><number>x</number><number>y</number><number>x</number><number>y</number><number>x</number><number>y</number><number>x</number><number>y</number><number>x</number><number>y</number><number>x</number><number>y</number><number>x</number><number>y</number>
              <number>x</number><number>y</number>
              </row><row><string></string>

                     <number shadow='shadow1'>0</number><number>.5</number><number shadow='shadow1' tooltip='15:00 DAL 0 SD 0 LI: 9-N.Novak kicks 74 yards from SD 35 to DAL -917-D.Harris Touchback.'>0.09</number><number>0.52</number>
<number shadow='shadow1' tooltip='14:26 1-10-DAL 30DAL 0 SD 0 LI: 1.69-T.Romo sacked at DAL 26 for -4 yards(91-K.Reyes).'>0.57</number><number>0.5</number>
<number shadow='shadow1' tooltip='13:45 2-14-DAL 26DAL 0 SD 0 LI: 1.39-T.Romo pass incomplete deep right to 88-D.Bryant.'>1.25</number><number>0.48</number>
<number shadow='shadow1' tooltip='13:39 3-14-DAL 26DAL 0 SD 0 LI: 1.1(Shotgun) 9-T.Romo pass incomplete short left to 17-D.Harris.'>1.35</number><number>0.46</number>
<number shadow='shadow1' tooltip='13:30 4-14-DAL 26DAL 0 SD 0 LI: 0.96-C.Jones punts 33 yards to SD 41 Center-91-L.Ladouceur downed by DAL-20-B.Webb.'>1.5</number><number>0.45</number>
<number shadow='shadow1' tooltip='13:20 1-10-SD 41DAL 0 SD 0 LI: 1.417-P.Rivers pass incomplete deep right to 86-V.Brown (39-B.Carr).'>1.67</number><number>0.47</number>
<number shadow='shadow1' tooltip='13:12 2-10-SD 41DAL 0 SD 0 LI: 1.2(Shotgun) 17-P.Rivers pass short left to 13-K.Allen to SD 46 for 5 yards(42-B.Church).'>1.8</number><number>0.47</number>
<number shadow='shadow1' tooltip='12:29 3-5-SD 46DAL 0 SD 0 LI: 1.1(Shotgun) 17-P.Rivers pass short middle to 86-V.Brown to 50 for 4 yards(32-O.Scandrick).'>2.52</number><number>0.51</number>
<number shadow='shadow1' tooltip='11:57 4-1-50DAL 0 SD 0 LI: 0.65-M.Scifres punts 32 yards to DAL 18 Center-47-M.Windt downed by SD-51-L.English.'>3.05</number><number>0.51</number>
<number shadow='shadow1' tooltip='11:45 1-10-DAL 18DAL 0 SD 0 LI: 1.629-D.Murray left tackle to DAL 23 for 5 yards(56-D.Butler 96-J.Johnson).'>3.25</number><number>0.51</number>
<number shadow='shadow1' tooltip='11:11 2-5-DAL 23DAL 0 SD 0 LI: 1.429-D.Murray left end to DAL 26 for 3 yards(94-C.Liuget).'>3.82</number><number>0.51</number>
<number shadow='shadow1' tooltip='10:24 3-2-DAL 26DAL 0 SD 0 LI: 1.4(Shotgun) 9-T.Romo pass incomplete short left to 88-D.Bryant (22-D.Cox).'>4.6</number><number>0.46</number>
<number shadow='shadow1' tooltip='10:19 4-2-DAL 26DAL 0 SD 0 LI: 0.96-C.Jones punts 51 yards to SD 23 Center-91-L.Ladouceur11-E.Royal to SD 35 for 12 yards(55-E.Jones).'>4.68</number><number>0.46</number>
<number shadow='shadow1' tooltip='10:06 1-10-SD 35DAL 0 SD 0 LI: 1.424-R.Mathews left end to SD 37 for 2 yards(50-S.Lee).'>4.9</number><number>0.47</number>
<number shadow='shadow1' tooltip='9:27 2-8-SD 37DAL 0 SD 0 LI: 1.3(Shotgun) 33-L.McClain up the middle to SD 42 for 5 yards(96-N.Hayden 52-J.Durant).'>5.55</number><number>0.47</number>
<number shadow='shadow1' tooltip='8:46 3-3-SD 42DAL 0 SD 0 LI: 1.2(Shotgun) PENALTY on SD-63-J.Troutman False Start 5 yards enforced at SD 42 - No Play.'>6.23</number><number>0.49</number>
<number shadow='shadow1' tooltip='8:23 3-8-SD 37DAL 0 SD 0 LI: 1.1(Shotgun) 17-P.Rivers pass deep left to 13-K.Allen to DAL 32 for 31 yards(50-S.Lee).'>6.62</number><number>0.39</number>
<number shadow='shadow1' tooltip='7:53 1-10-DAL 32DAL 0 SD 0 LI: 1.5(Shotgun) 17-P.Rivers pass short middle to 85-A.Gates to DAL 26 for 6 yards(50-S.Lee).'>7.12</number><number>0.38</number>
<number shadow='shadow1' tooltip='7:12 2-4-DAL 26DAL 0 SD 0 LI: 1.5(Shotgun) 17-P.Rivers pass deep right to 39-D.Woodhead for 26 yards TOUCHDOWN.'>7.8</number><number>0.29</number>
<number shadow='shadow1' tooltip='7:12 DAL 0 SD 0 LI: 9-N.Novak extra point is GOOD Center-47-M.Windt Holder-5-M.Scifres.'>7.84</number><number>0.29</number>
<number shadow='shadow1' tooltip='7:12 DAL 0 SD 7 LI: 9-N.Novak kicks 74 yards from SD 35 to DAL -917-D.Harris Touchback.'>7.89</number><number>0.28</number>
<number shadow='shadow1' tooltip='7:05 1-10-DAL 20DAL 0 SD 7 LI: 1.59-T.Romo pass incomplete short left to 83-T.Williams.'>7.92</number><number>0.27</number>
<number shadow='shadow1' tooltip='7:00 2-10-DAL 20DAL 0 SD 7 LI: 1.4(Shotgun) 9-T.Romo pass short middle to 82-J.Witten to DAL 27 for 7 yards(32-E.Weddle).'>8</number><number>0.28</number>
<number shadow='shadow1' tooltip='6:19 3-3-DAL 27DAL 0 SD 7 LI: 1.3(Shotgun) 9-T.Romo sacked at DAL 19 for -8 yards(94-C.Liuget).'>8.68</number><number>0.23</number>
<number shadow='shadow1' tooltip='5:53 4-11-DAL 19DAL 0 SD 7 LI: 16-C.Jones punts 46 yards to SD 35 Center-91-L.Ladouceur fair catch by 11-E.Royal.'>9.12</number><number>0.25</number>
<number shadow='shadow1' tooltip='5:45 1-10-SD 35DAL 0 SD 7 LI: 124-R.Mathews right tackle to SD 37 for 2 yards(96-N.Hayden).'>9.25</number><number>0.24</number>
<number shadow='shadow1' tooltip='5:05 2-8-SD 37DAL 0 SD 7 LI: 1(Shotgun) 24-R.Mathews left end to SD 44 for 7 yards(54-B.Carter).'>9.92</number><number>0.22</number>
<number shadow='shadow1' tooltip='4:22 3-1-SD 44DAL 0 SD 7 LI: 1.133-L.McClain up the middle to 50 for 6 yards(96-N.Hayden 50-S.Lee).'>10.63</number><number>0.2</number>
<number shadow='shadow1' tooltip='3:44 1-10-50DAL 0 SD 7 LI: 1.324-R.Mathews up the middle to DAL 49 for 1 yard(50-S.Lee 54-B.Carter).'>11.27</number><number>0.22</number>
<number shadow='shadow1' tooltip='3:03 2-9-DAL 49DAL 0 SD 7 LI: 1(Shotgun) 17-P.Rivers pass short left to 85-A.Gates to DAL 49 for no gain (42-B.Church).'>11.95</number><number>0.24</number>
<number shadow='shadow1' tooltip='2:21 3-9-DAL 49DAL 0 SD 7 LI: 0.8(Shotgun) 17-P.Rivers pass incomplete (97-J.Hatcher).'>12.65</number><number>0.28</number>
<number shadow='shadow1' tooltip='2:14 4-9-DAL 49DAL 0 SD 7 LI: 0.45-M.Scifres punts 34 yards to DAL 15 Center-47-M.Windt fair catch by 17-D.Harris.'>12.77</number><number>0.27</number>
<number shadow='shadow1' tooltip='2:08 1-10-DAL 15DAL 0 SD 7 LI: 1.529-D.Murray left tackle to DAL 21 for 6 yards(26-J.Patrick)SD-26-J.Patrick was injured during the play.'>12.87</number><number>0.28</number>
<number shadow='shadow1' tooltip='1:31 2-4-DAL 21DAL 0 SD 7 LI: 1.5(Shotgun) 9-T.Romo pass short middle to 11-C.Beasley to DAL 26 for 5 yards(50-M.Teo).'>13.48</number><number>0.29</number>
<number shadow='shadow1' tooltip='0:57 1-10-DAL 26DAL 0 SD 7 LI: 1.49-T.Romo pass short left to 83-T.Williams to DAL 36 for 10 yards(22-D.Cox 38-M.Gilchrist).'>14.05</number><number>0.3</number>
<number shadow='shadow1' tooltip='0:16 1-10-DAL 36DAL 0 SD 7 LI: 1.2(Shotgun) 9-T.Romo pass short right to 83-T.Williams to DAL 46 for 10 yards(31-R.Marshall).'>14.73</number><number>0.32</number>
<number shadow='shadow1' tooltip='15:00 1-10-DAL 46DAL 0 SD 7 LI: 1.2(Shotgun) 9-T.Romo pass short right to 17-D.Harris to SD 41 for 13 yards(31-R.Marshall).'>15</number><number>0.34</number>
<number shadow='shadow1' tooltip='14:33 1-10-SD 41DAL 0 SD 7 LI: 1.1(Shotgun) 29-D.Murray right tackle to SD 39 for 2 yards(98-S.Lissemore)PENALTY on SD-56-D.Butler Face Mask (15 Yards) 15 yards enforced at SD 39.'>15.45</number><number>0.36</number>
<number shadow='shadow1' tooltip='14:05 1-10-SD 24DAL 0 SD 7 LI: 0.9(Shotgun) 9-T.Romo pass short left to 83-T.Williams ran ob at SD 11 for 13 yards.'>15.92</number><number>0.44</number>
<number shadow='shadow1' tooltip='13:58 1-10-SD 11DAL 0 SD 7 LI: 1.429-D.Murray left tackle to SD 5 for 6 yards(56-D.Butler 38-M.Gilchrist).'>16.03</number><number>0.44</number>
<number shadow='shadow1' tooltip='13:15 2-4-SD 5DAL 0 SD 7 LI: 1.49-T.Romo pass short right to 88-D.Bryant for 5 yards TOUCHDOWN.'>16.75</number><number>0.47</number>
<number shadow='shadow1' tooltip='13:15 DAL 0 SD 7 LI: 5-D.Bailey extra point is GOOD Center-91-L.Ladouceur Holder-6-C.Jones.'>16.79</number><number>0.47</number>
<number shadow='shadow1' tooltip='13:15 DAL 7 SD 7 LI: 5-D.Bailey kicks 65 yards from DAL 35 to end zone Touchback.'>16.84</number><number>0.48</number>
<number shadow='shadow1' tooltip='12:34 1-10-SD 31DAL 7 SD 7 LI: 1.4(Shotgun) 17-P.Rivers pass to 85-A.Gates to SD 36 for 5 yards(32-O.Scandrick)DAL-32-O.Scandrick was injured during the play.'>17.43</number><number>0.47</number>
<number shadow='shadow1' tooltip='12:06 2-5-SD 36DAL 7 SD 7 LI: 1.224-R.Mathews up the middle to SD 42 for 6 yards(54-B.Carter).'>17.9</number><number>0.45</number>
<number shadow='shadow1' tooltip='11:26 1-10-SD 42DAL 7 SD 7 LI: 1.324-R.Mathews right end to SD 38 for -4 yards(97-J.Hatcher 26-W.Allen).'>18.57</number><number>0.48</number>
<number shadow='shadow1' tooltip='10:45 2-14-SD 38DAL 7 SD 7 LI: 1.1(Shotgun) PENALTY on SD-79-M.Harris False Start 5 yards enforced at SD 38 - No Play.'>19.25</number><number>0.5</number>
<number shadow='shadow1' tooltip='10:23 2-19-SD 33DAL 7 SD 7 LI: 1(Shotgun) 17-P.Rivers pass short right to 39-D.Woodhead to SD 31 for -2 yards(50-S.Lee).'>19.62</number><number>0.53</number>
<number shadow='shadow1' tooltip='9:45 3-21-SD 31DAL 7 SD 7 LI: 0.7(Shotgun) 23-R.Brown up the middle to SD 38 for 7 yards(99-G.Selvie 50-S.Lee).'>20.25</number><number>0.53</number>
<number shadow='shadow1' tooltip='9:18 4-14-SD 38DAL 7 SD 7 LI: 0.65-M.Scifres punts 42 yards to DAL 20 Center-47-M.Windt17-D.Harris pushed ob at SD 42 for 38 yards(5-M.Scifres).'>20.7</number><number>0.58</number>
<number shadow='shadow1' tooltip='9:02 1-10-SD 42DAL 7 SD 7 LI: 1.329-D.Murray left end to SD 42 for no gain (38-M.Gilchrist).'>20.97</number><number>0.56</number>
<number shadow='shadow1' tooltip='8:32 2-10-SD 42DAL 7 SD 7 LI: 1.1(Shotgun) 9-T.Romo pass short left to 29-D.Murray to SD 38 for 4 yards(22-D.Cox).'>21.47</number><number>0.55</number>
<number shadow='shadow1' tooltip='7:48 3-6-SD 38DAL 7 SD 7 LI: 1(Shotgun) 9-T.Romo pass incomplete short left to 82-J.Witten (32-E.Weddle).'>22.2</number><number>0.5</number>
<number shadow='shadow1' tooltip='7:43 4-6-SD 38DAL 7 SD 7 LI: 0.55-D.Bailey 56 yard field goal is No Good Wide Left Center-91-L.Ladouceur Holder-6-C.Jones.'>22.28</number><number>0.44</number>
<number shadow='shadow1' tooltip='7:38 1-10-SD 46DAL 7 SD 7 LI: 1.3(Shotgun) 17-P.Rivers pass short left to 24-R.Mathews pushed ob at DAL 40 for 14 yards(24-M.Claiborne).'>22.37</number><number>0.41</number>
<number shadow='shadow1' tooltip='7:26 1-10-DAL 40DAL 7 SD 7 LI: 1.4(Shotgun) 17-P.Rivers pass short left to 13-K.Allen to DAL 25 for 15 yards(24-M.Claiborne).'>22.57</number><number>0.38</number>
<number shadow='shadow1' tooltip='6:59 1-10-DAL 25DAL 7 SD 7 LI: 1.5(Shotgun) 24-R.Mathews left end to DAL 20 for 5 yards(54-B.Carter).'>23.02</number><number>0.35</number>
<number shadow='shadow1' tooltip='6:33 2-5-DAL 20DAL 7 SD 7 LI: 1.7(Shotgun) 24-R.Mathews left end to DAL 19 for 1 yard(54-B.Carter).'>23.45</number><number>0.36</number>
<number shadow='shadow1' tooltip='5:51 3-4-DAL 19DAL 7 SD 7 LI: 1.5(Shotgun) 17-P.Rivers pass short middle to 86-V.Brown to DAL 18 for 1 yard(59-E.Sims).'>24.15</number><number>0.41</number>
<number shadow='shadow1' tooltip='5:16 4-3-DAL 18DAL 7 SD 7 LI: 19-N.Novak 36 yard field goal is GOOD Center-47-M.Windt Holder-5-M.Scifres.'>24.73</number><number>0.4</number>
<number shadow='shadow1' tooltip='5:16 DAL 7 SD 10 LI: 9-N.Novak kicks 70 yards from SD 35 to DAL -517-D.Harris to DAL 28 for 33 yards(32-E.Weddle 97-B.Bird).'>24.82</number><number>0.4</number>
<number shadow='shadow1' tooltip='5:05 1-10-DAL 28DAL 7 SD 10 LI: 19-T.Romo pass short right to 88-D.Bryant to DAL 42 for 14 yards(50-M.Teo).'>24.92</number><number>0.44</number>
<number shadow='shadow1' tooltip='4:31 1-10-DAL 42DAL 7 SD 10 LI: 1.229-D.Murray right end to DAL 45 for 3 yards(92-C.Thomas 31-R.Marshall).'>25.48</number><number>0.44</number>
<number shadow='shadow1' tooltip='3:52 2-7-DAL 45DAL 7 SD 10 LI: 1.229-D.Murray up the middle to SD 41 for 14 yards(26-J.Patrick)SD-93-D.Freeney was injured during the play.'>26.13</number><number>0.48</number>
<number shadow='shadow1' tooltip='3:25 1-10-SD 41DAL 7 SD 10 LI: 1.4(Shotgun) 25-L.Dunbar right end to SD 34 for 7 yards(56-D.Butler).'>26.58</number><number>0.49</number>
<number shadow='shadow1' tooltip='2:44 2-3-SD 34DAL 7 SD 10 LI: 1.39-T.Romo pass short middle to 88-D.Bryant for 34 yards TOUCHDOWN.'>27.27</number><number>0.62</number>
<number shadow='shadow1' tooltip='2:44 DAL 7 SD 10 LI: 5-D.Bailey extra point is GOOD Center-91-L.Ladouceur Holder-6-C.Jones.'>27.31</number><number>0.62</number>
<number shadow='shadow1' tooltip='2:44 DAL 14 SD 10 LI: 5-D.Bailey kicks 73 yards from DAL 35 to SD -839-D.Woodhead Touchback.'>27.36</number><number>0.63</number>
<number shadow='shadow1' tooltip='2:36 1-10-SD 20DAL 14 SD 10 LI: 1.2(Shotgun) 17-P.Rivers pass short right to 39-D.Woodhead to SD 30 for 10 yards(42-B.Church).'>27.4</number><number>0.62</number>
<number shadow='shadow1' tooltip='2:19 1-10-SD 30DAL 14 SD 10 LI: 1.2(Shotgun) 17-P.Rivers sacked at SD 23 for -7 yards(99-G.Selvie).'>27.68</number><number>0.66</number>
<number shadow='shadow1' tooltip='2:00 2-17-SD 23DAL 14 SD 10 LI: 0.9(Shotgun) 17-P.Rivers pass short right to 86-V.Brown pushed ob at SD 42 for 19 yards(39-B.Carr).'>28</number><number>0.59</number>
<number shadow='shadow1' tooltip='1:54 1-10-SD 42DAL 14 SD 10 LI: 1.3(Shotgun) 17-P.Rivers pass short middle to 39-D.Woodhead to SD 49 for 7 yards(42-B.Church).'>28.1</number><number>0.59</number>
<number shadow='shadow1' tooltip='1:32 2-3-SD 49DAL 14 SD 10 LI: 1.3(Shotgun) 17-P.Rivers pass short middle INTERCEPTED by 50-S.Lee (97-J.Hatcher) at DAL 4850-S.Lee for 52 yards TOUCHDOWNSD-76-D.Fluker was injured during the play.'>28.47</number><number>0.83</number>
<number shadow='shadow1' tooltip='1:32 DAL 14 SD 10 LI: 5-D.Bailey extra point is GOOD Center-91-L.Ladouceur Holder-6-C.Jones.'>28.51</number><number>0.83</number>
<number shadow='shadow1' tooltip='1:32 DAL 21 SD 10 LI: 5-D.Bailey kicks 63 yards from DAL 35 to SD 239-D.Woodhead to SD 20 for 18 yards(21-J.Randle).'>28.56</number><number>0.85</number>
<number shadow='shadow1' tooltip='1:13 1-10-SD 10DAL 21 SD 10 LI: 0.7(Shotgun) 17-P.Rivers pass short middle to 85-A.Gates to SD 19 for 9 yards(50-S.Lee).'>28.78</number><number>0.84</number>
<number shadow='shadow1' tooltip='0:54 2-1-SD 19DAL 21 SD 10 LI: 1(Shotgun) 17-P.Rivers pass to 85-A.Gates to SD 27 for 8 yards(50-S.Lee).'>29.1</number><number>0.83</number>
<number shadow='shadow1' tooltip='0:49 1-10-SD 27DAL 21 SD 10 LI: 1(Shotgun) 17-P.Rivers pass deep left to 11-E.Royal pushed ob at DAL 45 for 28 yards(24-M.Claiborne).'>29.18</number><number>0.78</number>
<number shadow='shadow1' tooltip='0:41 1-10-DAL 45DAL 21 SD 10 LI: 1.2(Shotgun) 17-P.Rivers pass short left to 85-A.Gates pushed ob at DAL 31 for 14 yards(24-M.Claiborne).'>29.32</number><number>0.76</number>
<number shadow='shadow1' tooltip='0:35 1-10-DAL 31DAL 21 SD 10 LI: 1.2(Shotgun) 17-P.Rivers pass incomplete short left to 39-D.Woodhead.'>29.42</number><number>0.77</number>
<number shadow='shadow1' tooltip='0:32 2-10-DAL 31DAL 21 SD 10 LI: 1.1(Shotgun) 17-P.Rivers pass incomplete deep left to 86-V.Brown.'>29.47</number><number>0.79</number>
<number shadow='shadow1' tooltip='0:26 3-10-DAL 31DAL 21 SD 10 LI: 0.9(Shotgun) 17-P.Rivers pass short middle to 83-J.Phillips to DAL 24 for 7 yards(39-B.Carr 54-B.Carter).'>29.57</number><number>0.81</number>
<number shadow='shadow1' tooltip='0:02 4-3-DAL 24DAL 21 SD 10 LI: 0.69-N.Novak 42 yard field goal is GOOD Center-47-M.Windt Holder-5-M.Scifres.'>29.97</number><number>0.79</number>
<number shadow='shadow1' tooltip='0:02 DAL 21 SD 13 LI: 5-D.Bailey kicks 70 yards from DAL 35 to SD -539-D.Woodhead Touchback.'>30.06</number><number>0.76</number>
<number shadow='shadow1' tooltip='14:30 2-9-SD 21DAL 21 SD 13 LI: 1(Shotgun) 17-P.Rivers pass short right to 86-V.Brown to SD 23 for 2 yards(50-S.Lee).'>30.5</number><number>0.78</number>
<number shadow='shadow1' tooltip='13:47 3-7-SD 23DAL 21 SD 13 LI: 0.9(Shotgun) 17-P.Rivers pass short left to 86-V.Brown to SD 35 for 12 yards(32-O.Scandrick 24-M.Claiborne).'>31.22</number><number>0.74</number>
<number shadow='shadow1' tooltip='13:14 1-10-SD 35DAL 21 SD 13 LI: 1.1(Shotgun) 17-P.Rivers pass short left to 11-E.Royal to SD 37 for 2 yards(99-G.Selvie 96-N.Hayden).'>31.77</number><number>0.74</number>
<number shadow='shadow1' tooltip='12:37 2-8-SD 37DAL 21 SD 13 LI: 1(Shotgun) 17-P.Rivers pass short middle to 85-A.Gates to SD 44 for 7 yards(54-B.Carter).'>32.38</number><number>0.73</number>
<number shadow='shadow1' tooltip='11:54 3-1-SD 44DAL 21 SD 13 LI: 1.1(Shotgun) 17-P.Rivers pass short left to 85-A.Gates to SD 49 for 5 yards(42-B.Church).'>33.1</number><number>0.72</number>
<number shadow='shadow1' tooltip='11:22 1-10-SD 49DAL 21 SD 13 LI: 1.1(Shotgun) 17-P.Rivers pass deep left to 85-A.Gates to DAL 25 for 26 yards(24-M.Claiborne).'>33.63</number><number>0.67</number>
<number shadow='shadow1' tooltip='10:43 1-10-DAL 25DAL 21 SD 13 LI: 1.2(Shotgun) 39-D.Woodhead up the middle to DAL 16 for 9 yards(42-B.Church).'>34.28</number><number>0.63</number>
<number shadow='shadow1' tooltip='10:19 2-1-DAL 16DAL 21 SD 13 LI: 1.5(Shotgun) 39-D.Woodhead up the middle to DAL 13 for 3 yards(50-S.Lee 97-J.Hatcher).'>34.68</number><number>0.61</number>
<number shadow='shadow1' tooltip='9:39 1-10-DAL 13DAL 21 SD 13 LI: 1.6(Shotgun) 17-P.Rivers pass short left to 39-D.Woodhead for 13 yards TOUCHDOWN.'>35.35</number><number>0.57</number>
<number shadow='shadow1' tooltip='9:39 DAL 21 SD 13 LI: 9-N.Novak extra point is GOOD Center-47-M.Windt Holder-5-M.Scifres.'>35.39</number><number>0.57</number>
<number shadow='shadow1' tooltip='9:39 DAL 21 SD 20 LI: 9-N.Novak kicks 65 yards from SD 35 to end zone Touchback.'>35.44</number><number>0.55</number>
<number shadow='shadow1' tooltip='9:32 1-10-DAL 20DAL 21 SD 20 LI: 1.5(Shotgun) 29-D.Murray right tackle to DAL 23 for 3 yards(91-K.Reyes 32-E.Weddle).'>35.47</number><number>0.56</number>
<number shadow='shadow1' tooltip='8:50 2-7-DAL 23DAL 21 SD 20 LI: 1.5(Shotgun) PENALTY on DAL-11-C.Beasley False Start 5 yards enforced at DAL 23 - No Play.'>36.17</number><number>0.54</number>
<number shadow='shadow1' tooltip='8:24 2-12-DAL 18DAL 21 SD 20 LI: 1.4(Shotgun) 9-T.Romo pass short right to 29-D.Murray to DAL 27 for 9 yards(56-D.Butler 94-C.Liuget).'>36.6</number><number>0.56</number>
<number shadow='shadow1' tooltip='8:00 3-3-DAL 27DAL 21 SD 20 LI: 1.49-T.Romo pass short middle to 11-C.Beasley to DAL 32 for 5 yards(52-R.Walker).'>37</number><number>0.58</number>
<number shadow='shadow1' tooltip='7:38 1-10-DAL 32DAL 21 SD 20 LI: 1.529-D.Murray up the middle to DAL 36 for 4 yards(38-M.Gilchrist 94-C.Liuget)PENALTY on SD-56-D.Butler Unnecessary Roughness 15 yards enforced at DAL 36.'>37.37</number><number>0.62</number>
<number shadow='shadow1' tooltip='7:13 1-10-SD 49DAL 21 SD 20 LI: 1.429-D.Murray left end to 50 for -1 yards(94-C.Liuget 96-J.Johnson).'>37.78</number><number>0.6</number>
<number shadow='shadow1' tooltip='6:28 2-11-50DAL 21 SD 20 LI: 1.3(Shotgun) 9-T.Romo pass incomplete short right to 82-J.Witten (91-K.Reyes).'>38.53</number><number>0.57</number>
<number shadow='shadow1' tooltip='6:24 3-11-50DAL 21 SD 20 LI: 1(Shotgun) 9-T.Romo pass incomplete short left to 88-D.Bryant.'>38.6</number><number>0.54</number>
<number shadow='shadow1' tooltip='6:18 4-11-50DAL 21 SD 20 LI: 0.76-C.Jones punts 29 yards to SD 21 Center-91-L.Ladouceur fair catch by 11-E.RoyalPENALTY on SD-96-J.Johnson Offensive Holding 10 yards enforced at SD 21.'>38.7</number><number>0.56</number>
<number shadow='shadow1' tooltip='6:09 1-10-SD 11DAL 21 SD 20 LI: 1.8(Shotgun) 17-P.Rivers pass deep left to 13-K.Allen ran ob at SD 30 for 19 yards.'>38.85</number><number>0.51</number>
<number shadow='shadow1' tooltip='5:41 1-10-SD 30DAL 21 SD 20 LI: 1.6(Shotgun) 24-R.Mathews left end to SD 37 for 7 yards(59-E.Sims).'>39.32</number><number>0.51</number>
<number shadow='shadow1' tooltip='5:06 2-3-SD 37DAL 21 SD 20 LI: 1.4(Shotgun) 17-P.Rivers pass short left to 24-R.Mathews to SD 44 for 7 yards(32-O.Scandrick 50-S.Lee).'>39.9</number><number>0.48</number>
<number shadow='shadow1' tooltip='4:32 1-10-SD 44DAL 21 SD 20 LI: 1.6(Shotgun) 24-R.Mathews left guard to SD 49 for 5 yards(70-D.Nevis 51-K.Wilber).'>40.47</number><number>0.49</number>
<number shadow='shadow1' tooltip='3:48 2-5-SD 49DAL 21 SD 20 LI: 1.4(Shotgun) 17-P.Rivers pass short left to 13-K.Allen to DAL 41 for 10 yards(24-M.Claiborne).'>41.2</number><number>0.45</number>
<number shadow='shadow1' tooltip='3:13 1-10-DAL 41DAL 21 SD 20 LI: 1.6(Shotgun) 39-D.Woodhead up the middle to DAL 37 for 4 yards(97-J.Hatcher 27-J.Wilcox).'>41.78</number><number>0.46</number>
<number shadow='shadow1' tooltip='2:32 2-6-DAL 37DAL 21 SD 20 LI: 1.4(Shotgun) 17-P.Rivers pass short left to 11-E.Royal to DAL 25 for 12 yards(59-E.Sims 96-N.Hayden).'>42.47</number><number>0.41</number>
<number shadow='shadow1' tooltip='1:51 1-10-DAL 25DAL 21 SD 20 LI: 1.7(Shotgun) 39-D.Woodhead up the middle to DAL 11 for 14 yards(50-S.Lee).'>43.15</number><number>0.31</number>
<number shadow='shadow1' tooltip='1:13 1-10-DAL 11DAL 21 SD 20 LI: 2.4(Shotgun) 17-P.Rivers pass short right to 86-V.Brown to DAL 10 for 1 yard(99-G.Selvie).'>43.78</number><number>0.32</number>
<number shadow='shadow1' tooltip='0:31 2-9-DAL 10DAL 21 SD 20 LI: 2.3(Shotgun) 17-P.Rivers pass incomplete short middle to 86-V.Brown (32-O.Scandrick)PENALTY on DAL-32-O.Scandrick Defensive Pass Interference 3 yards enforced at DAL 10 - No Play.'>44.48</number><number>0.3</number>
<number shadow='shadow1' tooltip='0:26 1-7-DAL 7DAL 21 SD 20 LI: 2.5(Shotgun) 39-D.Woodhead right guard to DAL 5 for 2 yards(50-S.Lee).'>44.57</number><number>0.29</number>
<number shadow='shadow1' tooltip='15:00 2-5-DAL 5DAL 21 SD 20 LI: 2.6(Shotgun) 17-P.Rivers pass incomplete short right to 13-K.Allen.'>45</number><number>0.34</number>
<number shadow='shadow1' tooltip='14:54 3-5-DAL 5DAL 21 SD 20 LI: 2.1(Shotgun) 17-P.Rivers pass incomplete short right to 39-D.Woodhead (99-G.Selvie).'>45.1</number><number>0.43</number>
<number shadow='shadow1' tooltip='14:50 4-5-DAL 5DAL 21 SD 20 LI: 1.29-N.Novak 23 yard field goal is GOOD Center-47-M.Windt Holder-5-M.Scifres.'>45.17</number><number>0.44</number>
<number shadow='shadow1' tooltip='14:50 DAL 21 SD 23 LI: 9-N.Novak kicks 70 yards from SD 35 to DAL -517-D.Harris to DAL 23 for 28 yards(16-S.Ajirotutu 25-D.Stuckey).'>45.26</number><number>0.43</number>
<number shadow='shadow1' tooltip='14:41 1-10-DAL 23DAL 21 SD 23 LI: 1.729-D.Murray up the middle to DAL 32 for 9 yards(52-R.Walker 96-J.Johnson).'>45.32</number><number>0.45</number>
<number shadow='shadow1' tooltip='14:03 2-1-DAL 32DAL 21 SD 23 LI: 1.89-T.Romo pass short right to 29-D.Murray to DAL 38 for 6 yards(32-E.Weddle).'>45.95</number><number>0.47</number>
<number shadow='shadow1' tooltip='13:25 1-10-DAL 38DAL 21 SD 23 LI: 1.929-D.Murray left guard to DAL 44 for 6 yards(56-D.Butler 52-R.Walker).'>46.58</number><number>0.47</number>
<number shadow='shadow1' tooltip='12:44 2-4-DAL 44DAL 21 SD 23 LI: 1.79-T.Romo pass short right to 88-D.Bryant to SD 46 for 10 yards(26-J.Patrick).'>47.27</number><number>0.51</number>
<number shadow='shadow1' tooltip='12:11 1-10-SD 46DAL 21 SD 23 LI: 1.99-T.Romo pass short right to 88-D.Bryant to SD 40 for 6 yards(26-J.Patrick).'>47.82</number><number>0.52</number>
<number shadow='shadow1' tooltip='11:30 2-4-SD 40DAL 21 SD 23 LI: 2(Shotgun) 9-T.Romo pass short middle to 11-C.Beasley to SD 34 for 6 yards(38-M.Gilchrist)PENALTY on DAL-65-R.Leary Offensive Holding 10 yards enforced at SD 40 - No Play.'>48.5</number><number>0.46</number>
<number shadow='shadow1' tooltip='10:58 2-14-50DAL 21 SD 23 LI: 1.8(Shotgun) 9-T.Romo pass short left to 11-C.Beasley to SD 44 for 6 yards(31-R.Marshall).'>49.03</number><number>0.45</number>
<number shadow='shadow1' tooltip='10:18 3-8-SD 44DAL 21 SD 23 LI: 1.6(Shotgun) 9-T.Romo pass incomplete deep middle to 82-J.Witten (32-E.Weddle).'>49.7</number><number>0.37</number>
<number shadow='shadow1' tooltip='10:10 4-8-SD 44DAL 21 SD 23 LI: 0.86-C.Jones punts 44 yards to end zone Center-91-L.Ladouceur Touchback.'>49.83</number><number>0.36</number>
<number shadow='shadow1' tooltip='10:02 1-10-SD 20DAL 21 SD 23 LI: 2.4(Shotgun) 17-P.Rivers pass short left to 24-R.Mathews to SD 29 for 9 yards(59-E.Sims 94-D.Ware).'>49.97</number><number>0.33</number>
<number shadow='shadow1' tooltip='9:37 2-1-SD 29DAL 21 SD 23 LI: 2.6(Shotgun) 24-R.Mathews up the middle to SD 33 for 4 yards(42-B.Church).'>50.38</number><number>0.32</number>
<number shadow='shadow1' tooltip='9:02 1-10-SD 33DAL 21 SD 23 LI: 2.7(Shotgun) 24-R.Mathews left guard to SD 37 for 4 yards(97-J.Hatcher).'>50.97</number><number>0.29</number>
<number shadow='shadow1' tooltip='8:30 2-6-SD 37DAL 21 SD 23 LI: 3(Shotgun) 24-R.Mathews right tackle to SD 42 for 5 yards(50-S.Lee).'>51.5</number><number>0.27</number>
<number shadow='shadow1' tooltip='7:44 3-1-SD 42DAL 21 SD 23 LI: 2.9(Shotgun) 17-P.Rivers pass short right to 86-V.Brown to SD 44 for 2 yards(59-E.Sims).'>52.27</number><number>0.24</number>
<number shadow='shadow1' tooltip='7:02 1-10-SD 44DAL 21 SD 23 LI: 3(Shotgun) 17-P.Rivers pass deep middle to 85-A.Gates for 56 yards TOUCHDOWN.'>52.97</number><number>0.09</number>
<number shadow='shadow1' tooltip='7:02 DAL 21 SD 23 LI: 9-N.Novak extra point is GOOD Center-47-M.Windt Holder-5-M.Scifres.'>53.01</number><number>0.09</number>
<number shadow='shadow1' tooltip='7:02 DAL 21 SD 30 LI: 9-N.Novak kicks 68 yards from SD 35 to DAL -317-D.Harris to DAL 21 for 24 yards(89-L.Green).'>53.06</number><number>0.08</number>
<number shadow='shadow1' tooltip='6:49 1-10-DAL 21DAL 21 SD 30 LI: 0.5(Shotgun) 9-T.Romo pass short left to 83-T.Williams to DAL 30 for 9 yards(31-R.Marshall).'>53.18</number><number>0.1</number>
<number shadow='shadow1' tooltip='6:18 2-1-DAL 30DAL 21 SD 30 LI: 0.8(Shotgun) 9-T.Romo pass short right to 83-T.Williams to DAL 39 for 9 yards(26-J.Patrick).'>53.7</number><number>0.12</number>
<number shadow='shadow1' tooltip='5:59 1-10-DAL 39DAL 21 SD 30 LI: 0.8(Shotgun) 9-T.Romo pass short middle to 29-D.Murray to DAL 40 for 1 yard(56-D.Butler 38-M.Gilchrist)PENALTY on DAL-78-J.Parnell Offensive Holding 10 yards enforced at DAL 39 - No Play.'>54.02</number><number>0.1</number>
<number shadow='shadow1' tooltip='5:40 1-20-DAL 29DAL 21 SD 30 LI: 0.8(Shotgun) 9-T.Romo pass short middle to 82-J.Witten to DAL 40 for 11 yards(56-D.Butler).'>54.33</number><number>0.06</number>
<number shadow='shadow1' tooltip='5:14 2-9-DAL 40DAL 21 SD 30 LI: 0.2(Shotgun) 9-T.Romo pass incomplete deep middle to 82-J.WittenPENALTY on SD-56-D.Butler Defensive Pass Interference 25 yards enforced at DAL 40 - No Play.'>54.77</number><number>0.17</number>
<number shadow='shadow1' tooltip='5:09 1-10-SD 35DAL 21 SD 30 LI: 0.9(Shotgun) 9-T.Romo sacked at SD 42 for -7 yards(96-J.Johnson).'>54.85</number><number>0.06</number>
<number shadow='shadow1' tooltip='4:40 2-17-SD 42DAL 21 SD 30 LI: 0.1(Shotgun) 9-T.Romo pass short middle to 82-J.Witten to SD 34 for 8 yards(32-E.Weddle).'>55.33</number><number>0.12</number>
<number shadow='shadow1' tooltip='4:14 3-9-SD 34DAL 21 SD 30 LI: 0.6(Shotgun) 9-T.Romo pass short middle to 82-J.Witten to SD 24 for 10 yards(56-D.Butler).'>55.77</number><number>0.14</number>
<number shadow='shadow1' tooltip='3:49 1-10-SD 24DAL 21 SD 30 LI: 1.1(Shotgun) 9-T.Romo pass short middle to 29-D.Murray to SD 22 for 2 yards(56-D.Butler).'>56.18</number><number>0.06</number>
<number shadow='shadow1' tooltip='3:25 2-8-SD 22DAL 21 SD 30 LI: 0.5(Shotgun) 9-T.Romo pass incomplete deep middle to 82-J.Witten.'>56.58</number><number>0.15</number>
<number shadow='shadow1' tooltip='3:20 3-8-SD 22DAL 21 SD 30 LI: 1.4(Shotgun) 9-T.Romo scrambles up the middle to SD 7 for 15 yards(32-E.Weddle).'>56.67</number><number>0.01</number>
<number shadow='shadow1' tooltip='2:57 1-7-SD 7DAL 21 SD 30 LI: 0.19-T.Romo pass incomplete short right to 82-J.Witten (38-M.Gilchrist).'>57.05</number><number>0.11</number>
<number shadow='shadow1' tooltip='2:50 2-7-SD 7DAL 21 SD 30 LI: 1(Shotgun) 9-T.Romo pass short middle to 83-T.Williams to SD 1 for 6 yards(20-C.Butler; 32-E.Weddle)FUMBLES (20-C.Butler) RECOVERED by SD-31-R.Marshall at SD 0TouchbackThe Replay Assistant challenged the fumble ruling and the play was Upheld.'>57.17</number><number>0.01</number>
<number shadow='shadow1' tooltip='2:42 1-10-SD 20DAL 21 SD 30 LI: 0.7(Shotgun) 24-R.Mathews up the middle to SD 25 for 5 yards(50-S.Lee 54-B.Carter).'>57.3</number><number>0.02</number>
<number shadow='shadow1' tooltip='2:37 2-5-SD 25DAL 21 SD 30 LI: 0.9(Shotgun) 24-R.Mathews up the middle to SD 28 for 3 yards(59-E.Sims 42-B.Church).'>57.38</number><number>0.02</number>
<number shadow='shadow1' tooltip='2:32 3-2-SD 28DAL 21 SD 30 LI: 1.1(Shotgun) 24-R.Mathews up the middle to SD 28 for no gain (59-E.Sims)PENALTY on DAL-94-D.Ware Defensive Offside 5 yards enforced at SD 28 - No Play.'>57.47</number><number>0.01</number>
<number shadow='shadow1' tooltip='2:30 1-10-SD 33DAL 21 SD 30 LI: 1.2(Shotgun) 24-R.Mathews right end to SD 33 for no gain (50-S.Lee).'>57.5</number><number>0.02</number>
<number shadow='shadow1' tooltip='2:25 2-10-SD 33DAL 21 SD 30 LI: 1(Shotgun) 24-R.Mathews up the middle to SD 35 for 2 yards(42-B.Church).'>57.58</number><number>0.03</number>
<number shadow='shadow1' tooltip='2:00 3-8-SD 35DAL 21 SD 30 LI: 0.3(Shotgun) 24-R.Mathews right end to SD 41 for 6 yards(27-J.Wilcox).'>58</number><number>0.02</number>
<number shadow='shadow1' tooltip='1:11 4-2-SD 41DAL 21 SD 30 LI: 0.15-M.Scifres punts 51 yards to DAL 8 Center-47-M.Windt downed by SD-16-S.Ajirotutu.'>58.82</number><number>0.01</number>
<number shadow='shadow1' tooltip='1:02 1-10-DAL 8DAL 21 SD 30 LI: 0.1(Shotgun) 9-T.Romo pass short left to 82-J.Witten pushed ob at DAL 15 for 7 yards(31-R.Marshall).'>58.97</number><number>0.01</number>
<number shadow='shadow1' tooltip='0:56 2-3-DAL 15DAL 21 SD 30 LI: 0.1(Shotgun) 9-T.Romo pass short left to 83-T.Williams to DAL 29 for 14 yards(52-R.Walker).'>59.07</number><number>0.02</number>
<number shadow='shadow1' tooltip='0:34 1-10-DAL 29DAL 21 SD 30 LI: 0.1(Shotgun) 9-T.Romo pass short middle to 88-D.Bryant to DAL 41 for 12 yards(31-R.Marshall).'>59.43</number><number>0.01</number>
<number shadow='shadow1' tooltip='0:09 1-10-DAL 41DAL 21 SD 30 LI: 0.1(Shotgun) 9-T.Romo pass short middle to 29-D.Murray to DAL 46 for 5 yards(99-J.Wynn)FUMBLES (99-J.Wynn) recovered by DAL-9-T.Romo at DAL 409-T.Romo to DAL 40 for no gain (31-R.Marshall).'>59.85</number><number>0</number>
<number>60</number><number>0</number>
</row> </chart_data>
       <draw>



      <image x='45' y='298'  url='nfllogos/42x50png/DAL.gif'  layer='foreground' glow = 'glow1'/>
      <image x='45' y='350'  url='nfllogos/42x50png/SD.gif'     layer='foreground' glow = 'glow1'/>


      <rect x='130' y='300' width='250' height='40' fill_color='c0c0c0' bevel='bevel1' />
      <text x='135' y='300' width='250' height='40' h_align='left' v_align='middle' color='ffffff' shadow='shadow2' glow=''>Dallas Cowboys</text>

      <rect x='130' y='350' width='250' height='40' fill_color='087ac3' bevel='bevel1'  />
      <text x='135' y='350' width='250' height='40' h_align='left' v_align='middle' color='ffffff' shadow='shadow2' glow='winnerglow'>San Diego Chargers</text>

      <rect x='420' y='300' width='60' height='40' fill_color='c0c0c0' bevel='bevel1'  />
      <text x='420' y='300' width='60' height='40' h_align='center' v_align='middle' color='ffffff' shadow='shadow2' transition='none' glow=''>21</text>

      <rect x='420' y='350' width='60' height='40' fill_color='087ac3' bevel='bevel1' />
      <text x='420' y='350' width='60' height='40' h_align='center' v_align='middle' color='ffffff' shadow='shadow2' transition='none' glow='winnerglow'>30</text>

      <text x='-3' y='12'  width='60' height='40' h_align='center' v_align='middle' size='13' shadow='shadow2'>DALWin </text>
      <text x='-3' y='218' width='60' height='40' h_align='center' v_align='middle' size='13' shadow='shadow2'>SDWin </text>

     
              <rect x='540' y='300' width='100' height='35' fill_color='000000' fill_alpha='50'/>
              <text x='540' y='300' width='100' height='35' h_align='center' v_align='middle' color='ffffff' size='15' shadow='shadow2' >Final</text>

              <text x='540' y='340' width='40' h_align='center' color='000000' size='12' shadow='shadow2'>CBF</text>
              <text x='600' y='340' width='40' h_align='center' color='000000' size='12' shadow='shadow2'>EI</text>

              <rect x='540' y='360' width='40' height='30' fill_color='000000' fill_alpha='50' />
              <text x='540' y='360' width='40' height='30' size='12' h_align='center' v_align='middle' color='FFFFFF' shadow='shadow2'>7</text>

              <rect x='600' y='360' width='40' height='30' fill_color='000000' fill_alpha='50' />
              <text x='600' y='360' width='40' height='30' size='12' h_align='center' v_align='middle' color='FFFFFF' shadow='shadow2'>4.6</text>

              <text x='20' y='420' width='70' height='25' size='12' h_align='left' v_align='middle' color='000000' >9/29/2013</text>
              <text x='100' y='420' width='200' height='25' size='12' h_align='left' v_align='middle' color='000000' >Qualcomm Stadium</text>

   </draw></chart>